lib_justin_furuness/__init__.py
lib_justin_furuness/justin_furuness.py
lib_justin_furuness/test/__init__.py
lib_justin_furuness/test/test_justin_furuness.py
lib_justin_furuness-0.5.dist-info/METADATA
lib_justin_furuness-0.5.dist-info/RECORD
lib_justin_furuness-0.5.dist-info/WHEEL
lib_justin_furuness-0.5.dist-info/entry_points.txt
lib_justin_furuness-0.5.dist-info/top_level.txt
