Metadata-Version: 2.1
Name: lib-justin-furuness
Version: 0.5
Summary: Test that prints out Justin Furuness
Home-page: https://github.com/jfuruness/justin_furuness
Author: Justin Furuness
Author-email: jfuruness@gmail.com
License: UNKNOWN
Download-URL: https://github.com/jfuruness/justin_furuness
Keywords: Furuness,furuness,pypi,package
Platform: UNKNOWN
Classifier: Environment :: Console
Classifier: Intended Audience :: Developers
Classifier: License :: OSI Approved :: MIT License
Classifier: Operating System :: OS Independent
Classifier: Programming Language :: Python
Classifier: Programming Language :: Python :: 2
Classifier: Programming Language :: Python :: 3
Classifier: Topic :: Software Development :: Libraries :: Python Modules
Requires-Dist: pytest (==2.9.2)
